example.cpython-310-x86_64-linux-gnu.so
pyvsag-0.14.0.dist-info/WHEEL
pyvsag-0.14.0.dist-info/RECORD
pyvsag-0.14.0.dist-info/METADATA
pyvsag-0.14.0.dist-info/top_level.txt
pyvsag/_pyvsag.cpython-310-x86_64-linux-gnu.so
pyvsag/__init__.py
pyvsag/_version.py
pyvsag/libgfortran.so.5
pyvsag/libvsag.so
pyvsag/_version.py.in
pyvsag.libs/libgomp-a34b3233.so.1.0.0
pyvsag.libs/libaio-74c6bb01.so.1.0.1
pyvsag.libs/libquadmath-96973f99.so.0.0.0
